merge_ics/__init__.py
merge_ics/__main__.py
merge_ics/merge_ics.py
merge_ics-0.2.0.dist-info/DESCRIPTION.rst
merge_ics-0.2.0.dist-info/METADATA
merge_ics-0.2.0.dist-info/RECORD
merge_ics-0.2.0.dist-info/WHEEL
merge_ics-0.2.0.dist-info/entry_points.txt
merge_ics-0.2.0.dist-info/metadata.json
merge_ics-0.2.0.dist-info/top_level.txt
