Metadata-Version: 2.0
Name: merge-ics
Version: 0.2.0
Summary: Merge RFC5545 calendar files
Home-page: https://github.com/agraboso/merge_ics
Author: Alberto Garcia-Raboso
Author-email: agraboso@gmail.com
License: MIT
Keywords: RFC5545 ics calendar
Platform: any
Classifier: Programming Language :: Python
Classifier: Development Status :: 4 - Beta
Classifier: Environment :: Console
Classifier: Operating System :: OS Independent
Classifier: Natural Language :: English
Classifier: Topic :: Utilities
Classifier: License :: OSI Approved :: MIT License
Requires-Dist: PyYAML (>3)
Requires-Dist: icalendar (<=4,>=3.9.0)
Requires-Dist: requests (>=2.7.0)
